metmap/__init__.py
metmap/metmap.py
metmap-1.0.4.data/scripts/run_metmap.py
metmap-1.0.4.dist-info/METADATA
metmap-1.0.4.dist-info/WHEEL
metmap-1.0.4.dist-info/top_level.txt
metmap-1.0.4.dist-info/RECORD
