Metadata-Version: 2.1
Name: metmap
Version: 1.0.4
Summary: A tool for generating DNA MTase motif testing sequences
Home-page: https://github.com/cfblaeb/metmap
Author: Lasse Ebdrup Pedersen
Author-email: laeb@biosustain.dtu.dk
License: UNKNOWN
Platform: UNKNOWN
Classifier: Development Status :: 5 - Production/Stable
Classifier: Environment :: Console
Classifier: Intended Audience :: Science/Research
Classifier: Topic :: Scientific/Engineering :: Bio-Informatics
Classifier: License :: Free for non-commercial use
Requires-Python: >=3.6
Requires-Dist: biopython
